zotero_viewer/__init__.py
zotero_viewer/app.py
zotero_viewer/static/.DS_Store
zotero_viewer/static/css/styles.css
zotero_viewer/static/js/attachment-handler.js
zotero_viewer/static/js/item-details.js
zotero_viewer/static/js/item-search.js
zotero_viewer/static/js/item-sorter.js
zotero_viewer/static/js/main.js
zotero_viewer/static/js/tag-autocomplete.js
zotero_viewer/static/js/tag-operations.js
zotero_viewer/templates/index.html
zotero_viewer-0.1.3.dist-info/LICENSE
zotero_viewer-0.1.3.dist-info/METADATA
zotero_viewer-0.1.3.dist-info/WHEEL
zotero_viewer-0.1.3.dist-info/entry_points.txt
zotero_viewer-0.1.3.dist-info/top_level.txt
zotero_viewer-0.1.3.dist-info/RECORD
