Metadata-Version: 2.1
Name: zotero-viewer
Version: 0.1.3
Summary: A web-based viewer for Zotero references with advanced tagging and search capabilities
Home-page: https://github.com/herrlich10/zotero-viewer
Author: herrlich10
Author-email: herrlich10@gmail.com
License: MIT
Classifier: Programming Language :: Python :: 3
Classifier: License :: OSI Approved :: MIT License
Classifier: Operating System :: OS Independent
Classifier: Development Status :: 4 - Beta
Classifier: Intended Audience :: Science/Research
Classifier: Topic :: Scientific/Engineering :: Information Analysis
Requires-Python: >=3.6
License-File: LICENSE
Requires-Dist: flask>=2.0.0
Requires-Dist: click>=7.0
